zope.app.principalannotation-5.0-py3.9-nspkg.pth
zope/app/principalannotation/__init__.py
zope/app/principalannotation/bootstrap.py
zope/app/principalannotation/bootstrap.zcml
zope/app/principalannotation/browser.zcml
zope/app/principalannotation/configure.zcml
zope/app/principalannotation/interfaces.py
zope/app/principalannotation/tests.py
zope.app.principalannotation-5.0.dist-info/LICENSE.txt
zope.app.principalannotation-5.0.dist-info/METADATA
zope.app.principalannotation-5.0.dist-info/WHEEL
zope.app.principalannotation-5.0.dist-info/namespace_packages.txt
zope.app.principalannotation-5.0.dist-info/top_level.txt
zope.app.principalannotation-5.0.dist-info/RECORD
