Metadata-Version: 2.1
Name: zope.app.principalannotation
Version: 5.0
Summary: Bootstrap subscriber and browser menu item for zope.principalannotation
Home-page: http://github.com/zopefoundation/zope.app.principalannotation
Author: Zope Corporation and Contributors
Author-email: zope-dev@zope.dev
License: ZPL 2.1
Keywords: zope security principal annotation
Classifier: Development Status :: 5 - Production/Stable
Classifier: Environment :: Web Environment
Classifier: Intended Audience :: Developers
Classifier: License :: OSI Approved :: Zope Public License
Classifier: Programming Language :: Python
Classifier: Programming Language :: Python :: 3
Classifier: Programming Language :: Python :: 3.7
Classifier: Programming Language :: Python :: 3.8
Classifier: Programming Language :: Python :: 3.9
Classifier: Programming Language :: Python :: 3.10
Classifier: Programming Language :: Python :: 3.11
Classifier: Programming Language :: Python :: Implementation :: CPython
Classifier: Programming Language :: Python :: Implementation :: PyPy
Classifier: Natural Language :: English
Classifier: Operating System :: OS Independent
Classifier: Topic :: Internet :: WWW/HTTP
Classifier: Framework :: Zope :: 3
Requires-Python: >=3.7
License-File: LICENSE.txt
Requires-Dist: setuptools
Requires-Dist: transaction
Requires-Dist: zope.app.appsetup (>=4.0.0)
Requires-Dist: zope.processlifetime (>=2.1.0)
Requires-Dist: zope.principalannotation (>=4.0.0)
Provides-Extra: test
Requires-Dist: zope.container ; extra == 'test'
Requires-Dist: zope.testing ; extra == 'test'
Requires-Dist: zope.testrunner ; extra == 'test'
Requires-Dist: zope.traversing ; extra == 'test'
